{"13146":{"avgPick":67.17,"rank":39,"minPick":26,"maxPick":125,"drafts":6},"14871":{"avgPick":67.4,"rank":40,"minPick":23,"maxPick":172,"drafts":5},"15694":{"avgPick":52.67,"rank":32,"minPick":12,"maxPick":129,"drafts":6},"15797":{"avgPick":57.75,"rank":36,"minPick":34,"maxPick":153,"drafts":8},"16166":{"avgPick":89,"rank":41,"minPick":39,"maxPick":175,"drafts":5},"16287":{"avgPick":67,"rank":38,"minPick":10,"maxPick":151,"drafts":6},"16757":{"avgPick":59.33,"rank":37,"minPick":41,"maxPick":94,"drafts":6},"17462":{"avgPick":26.8,"rank":14,"minPick":2,"maxPick":137,"drafts":10},"17463":{"avgPick":20.5,"rank":10,"minPick":6,"maxPick":33,"drafts":8},"17472":{"avgPick":1.1,"rank":1,"minPick":1,"maxPick":2,"drafts":10},"17473":{"avgPick":4.8,"rank":4,"minPick":2,"maxPick":7,"drafts":10},"17474":{"avgPick":36.8,"rank":21,"minPick":15,"maxPick":104,"drafts":10},"17476":{"avgPick":25.4,"rank":13,"minPick":6,"maxPick":89,"drafts":10},"17477":{"avgPick":20.4,"rank":9,"minPick":8,"maxPick":67,"drafts":10},"17478":{"avgPick":39.7,"rank":25,"minPick":19,"maxPick":170,"drafts":10},"17481":{"avgPick":47.8,"rank":30,"minPick":19,"maxPick":144,"drafts":10},"17482":{"avgPick":32.8,"rank":19,"minPick":16,"maxPick":109,"drafts":10},"17485":{"avgPick":56.6,"rank":34,"minPick":24,"maxPick":172,"drafts":10},"17497":{"avgPick":2.67,"rank":2,"minPick":2,"maxPick":4,"drafts":9},"17498":{"avgPick":4.8,"rank":3,"minPick":3,"maxPick":10,"drafts":10},"17499":{"avgPick":6.6,"rank":5,"minPick":4,"maxPick":15,"drafts":10},"17500":{"avgPick":28.4,"rank":15,"minPick":9,"maxPick":132,"drafts":10},"17501":{"avgPick":13.56,"rank":6,"minPick":6,"maxPick":53,"drafts":9},"17502":{"avgPick":19.7,"rank":8,"minPick":7,"maxPick":64,"drafts":10},"17503":{"avgPick":42.3,"rank":27,"minPick":11,"maxPick":151,"drafts":10},"17505":{"avgPick":31.12,"rank":17,"minPick":25,"maxPick":40,"drafts":8},"17506":{"avgPick":22,"rank":11,"minPick":10,"maxPick":91,"drafts":9},"17507":{"avgPick":34.22,"rank":20,"minPick":17,"maxPick":103,"drafts":9},"17508":{"avgPick":45,"rank":29,"minPick":23,"maxPick":135,"drafts":9},"17509":{"avgPick":56.6,"rank":35,"minPick":21,"maxPick":202,"drafts":10},"17511":{"avgPick":38.33,"rank":23,"minPick":17,"maxPick":155,"drafts":9},"17512":{"avgPick":24.6,"rank":12,"minPick":8,"maxPick":84,"drafts":10},"17514":{"avgPick":43.3,"rank":28,"minPick":13,"maxPick":161,"drafts":10},"17517":{"avgPick":50.78,"rank":31,"minPick":31,"maxPick":154,"drafts":9},"17519":{"avgPick":42,"rank":26,"minPick":35,"maxPick":53,"drafts":5},"17520":{"avgPick":31.78,"rank":18,"minPick":9,"maxPick":120,"drafts":9},"17543":{"avgPick":17.5,"rank":7,"minPick":7,"maxPick":74,"drafts":10},"17544":{"avgPick":29,"rank":16,"minPick":8,"maxPick":129,"drafts":10},"17567":{"avgPick":37.4,"rank":22,"minPick":24,"maxPick":51,"drafts":5},"17607":{"avgPick":38.43,"rank":24,"minPick":19,"maxPick":49,"drafts":7},"17652":{"avgPick":56.3,"rank":33,"minPick":27,"maxPick":153,"drafts":10}}